causalmma_client/__init__.py
causalmma_client/engine.py
causalmma_client/training/__init__.py
causalmma_client/training/federated_trainer.py
causalmma_client/training/local_trainer.py
causalmma_client/training/models/__init__.py
causalmma_client/training/models/base_model.py
causalmma_client/training/models/outcome_model.py
causalmma_client/training/models/propensity_score.py
causalmma_client-1.0.0.dist-info/METADATA
causalmma_client-1.0.0.dist-info/WHEEL
causalmma_client-1.0.0.dist-info/top_level.txt
causalmma_client-1.0.0.dist-info/RECORD
